{
    "video_id": "sm37923786",
    "title": "【爆豪】クレイジー・ビート【カメラ配布】",
    "user_id": "49623021",
    "user_nickname": "Blau",
    "genre": "その他",
    "tags": [
        "MMDヒロアカ",
        "爆豪勝己",
        "クレイジー・ビート",
        "mmdカメラモーション配布あり",
        "僕のヒーローアカデミア"
    ],
    "view_data": [
        [
            1,
            39
        ],
        [
            2,
            78
        ],
        [
            4,
            114
        ],
        [
            5,
            138
        ],
        [
            7,
            153
        ],
        [
            10,
            174
        ],
        [
            12,
            182
        ],
        [
            13,
            187
        ],
        [
            15,
            198
        ],
        [
            16,
            223
        ],
        [
            18,
            235
        ],
        [
            21,
            258
        ],
        [
            23,
            268
        ],
        [
            24,
            284
        ],
        [
            26,
            293
        ],
        [
            27,
            314
        ],
        [
            29,
            336
        ],
        [
            31,
            345
        ],
        [
            34,
            355
        ],
        [
            36,
            357
        ],
        [
            37,
            358
        ],
        [
            40,
            369
        ],
        [
            42,
            374
        ],
        [
            43,
            378
        ],
        [
            45,
            383
        ],
        [
            46,
            387
        ],
        [
            48,
            393
        ],
        [
            49,
            399
        ],
        [
            51,
            415
        ],
        [
            53,
            425
        ],
        [
            56,
            437
        ],
        [
            58,
            439
        ],
        [
            61,
            446
        ],
        [
            63,
            449
        ],
        [
            64,
            452
        ],
        [
            65,
            456
        ],
        [
            68,
            460
        ],
        [
            69,
            464
        ]
    ]
}