{
    "video_id": "sm37921811",
    "title": "スターダスト・アイズ／浦西真理子",
    "user_id": "28825581",
    "user_nickname": "風見翔也",
    "genre": "未設定",
    "tags": [
        "うたスキ動画",
        "アニメ",
        "鎧伝",
        "サムライトルーパー"
    ],
    "view_data": [
        [
            9,
            6
        ],
        [
            10,
            6
        ],
        [
            12,
            7
        ],
        [
            13,
            9
        ],
        [
            15,
            9
        ],
        [
            18,
            9
        ],
        [
            20,
            9
        ],
        [
            21,
            9
        ],
        [
            23,
            9
        ],
        [
            24,
            9
        ],
        [
            26,
            9
        ],
        [
            29,
            11
        ],
        [
            31,
            11
        ],
        [
            32,
            11
        ],
        [
            34,
            11
        ],
        [
            35,
            11
        ],
        [
            37,
            11
        ],
        [
            39,
            11
        ],
        [
            42,
            11
        ],
        [
            44,
            11
        ],
        [
            45,
            11
        ],
        [
            46,
            11
        ],
        [
            50,
            11
        ],
        [
            51,
            11
        ],
        [
            53,
            11
        ],
        [
            54,
            11
        ],
        [
            55,
            11
        ],
        [
            57,
            11
        ],
        [
            59,
            11
        ],
        [
            61,
            11
        ],
        [
            64,
            11
        ],
        [
            66,
            11
        ],
        [
            69,
            11
        ],
        [
            71,
            11
        ],
        [
            72,
            11
        ],
        [
            73,
            11
        ],
        [
            76,
            11
        ],
        [
            77,
            11
        ]
    ]
}