{
    "video_id": "sm37923081",
    "title": "【Minecraft】地獄のようなスカイブロックで生きる　The Unusual SkyBlock v3.0 Part1　【ゆっくり実況】",
    "user_id": "84946794",
    "user_nickname": "senyazuki",
    "genre": "ゲーム",
    "tags": [
        "オリキャラでゆっくり実況",
        "tusb動画part1リンク",
        "senyazuki",
        "tusb攻略動画",
        "gdgdプレイ"
    ],
    "view_data": [
        [
            3,
            9
        ],
        [
            4,
            9
        ],
        [
            6,
            11
        ],
        [
            7,
            13
        ],
        [
            9,
            15
        ],
        [
            12,
            16
        ],
        [
            14,
            16
        ],
        [
            15,
            16
        ],
        [
            17,
            16
        ],
        [
            18,
            16
        ],
        [
            20,
            17
        ],
        [
            23,
            18
        ],
        [
            25,
            22
        ],
        [
            26,
            24
        ],
        [
            28,
            24
        ],
        [
            29,
            25
        ],
        [
            31,
            26
        ],
        [
            33,
            26
        ],
        [
            36,
            26
        ],
        [
            38,
            26
        ],
        [
            39,
            26
        ],
        [
            40,
            26
        ],
        [
            44,
            26
        ],
        [
            45,
            26
        ],
        [
            47,
            27
        ],
        [
            48,
            27
        ],
        [
            50,
            27
        ],
        [
            51,
            27
        ],
        [
            53,
            28
        ],
        [
            55,
            28
        ],
        [
            58,
            28
        ],
        [
            60,
            28
        ],
        [
            63,
            29
        ],
        [
            65,
            29
        ],
        [
            66,
            29
        ],
        [
            67,
            29
        ],
        [
            70,
            29
        ],
        [
            71,
            29
        ]
    ]
}