{
    "video_id": "sm37922322",
    "title": "【オリジナルMV】心做し/蝶々ｰp coverさいん【歌ってみた】",
    "user_id": "94342985",
    "user_nickname": "さいん",
    "genre": "音楽・サウンド",
    "tags": [
        "歌ってみた",
        "蝶々p",
        "心做し",
        "実況者",
        "初投稿"
    ],
    "view_data": [
        [
            7,
            4
        ],
        [
            8,
            4
        ],
        [
            9,
            4
        ],
        [
            11,
            4
        ],
        [
            12,
            4
        ],
        [
            16,
            4
        ],
        [
            17,
            4
        ],
        [
            19,
            4
        ],
        [
            20,
            4
        ],
        [
            22,
            4
        ],
        [
            23,
            4
        ],
        [
            27,
            6
        ],
        [
            28,
            6
        ],
        [
            30,
            6
        ],
        [
            31,
            7
        ],
        [
            33,
            8
        ],
        [
            35,
            8
        ],
        [
            36,
            8
        ],
        [
            40,
            8
        ],
        [
            41,
            9
        ],
        [
            42,
            9
        ],
        [
            44,
            9
        ],
        [
            47,
            9
        ],
        [
            49,
            10
        ],
        [
            50,
            10
        ],
        [
            52,
            10
        ],
        [
            53,
            10
        ],
        [
            54,
            10
        ],
        [
            57,
            11
        ],
        [
            58,
            11
        ],
        [
            62,
            12
        ],
        [
            63,
            12
        ],
        [
            67,
            12
        ],
        [
            68,
            12
        ],
        [
            70,
            12
        ],
        [
            71,
            12
        ],
        [
            73,
            12
        ],
        [
            75,
            12
        ]
    ]
}